README.txt
setup.cfg
setup.py
logilab/__init__.py
logilab.pylintinstaller.egg-info/PKG-INFO
logilab.pylintinstaller.egg-info/SOURCES.txt
logilab.pylintinstaller.egg-info/dependency_links.txt
logilab.pylintinstaller.egg-info/entry_points.txt
logilab.pylintinstaller.egg-info/namespace_packages.txt
logilab.pylintinstaller.egg-info/not-zip-safe
logilab.pylintinstaller.egg-info/requires.txt
logilab.pylintinstaller.egg-info/top_level.txt
logilab/astng/__init__.py
logilab/astng/__pkginfo__.py
logilab/astng/_exceptions.py
logilab/astng/astutils.py
logilab/astng/builder.py
logilab/astng/inference.py
logilab/astng/inspector.py
logilab/astng/lookup.py
logilab/astng/manager.py
logilab/astng/nodes.py
logilab/astng/raw_building.py
logilab/astng/scoped_nodes.py
logilab/astng/setup.py
logilab/astng/utils.py
logilab/astng/test/__init__.py
logilab/astng/test/regrtest.py
logilab/astng/test/unittest_builder.py
logilab/astng/test/unittest_inference.py
logilab/astng/test/unittest_inspector.py
logilab/astng/test/unittest_lookup.py
logilab/astng/test/unittest_manager.py
logilab/astng/test/unittest_nodes.py
logilab/astng/test/unittest_scoped_nodes.py
logilab/astng/test/unittest_utils.py
logilab/astng/test/data/__init__.py
logilab/astng/test/data/all.py
logilab/astng/test/data/format.py
logilab/astng/test/data/module.py
logilab/astng/test/data/module2.py
logilab/astng/test/data/noendingnewline.py
logilab/astng/test/data/nonregr.py
logilab/astng/test/data/notall.py
logilab/astng/test/data/SSL1/Connection1.py
logilab/astng/test/data/SSL1/__init__.py
logilab/astng/test/data/appl/__init__.py
logilab/astng/test/data/appl/myConnection.py
logilab/astng/test/data2/__init__.py
logilab/astng/test/data2/clientmodule_test.py
logilab/astng/test/data2/suppliermodule_test.py
logilab/common/__init__.py
logilab/common/__pkginfo__.py
logilab/common/adbh.py
logilab/common/astutils.py
logilab/common/bind.py
logilab/common/cache.py
logilab/common/changelog.py
logilab/common/clcommands.py
logilab/common/cli.py
logilab/common/compat.py
logilab/common/configuration.py
logilab/common/corbautils.py
logilab/common/daemon.py
logilab/common/date.py
logilab/common/db.py
logilab/common/debugger.py
logilab/common/decorators.py
logilab/common/deprecation.py
logilab/common/fileutils.py
logilab/common/graph.py
logilab/common/html.py
logilab/common/interface.py
logilab/common/logger.py
