Metadata-Version: 1.0
Name: logilab.pylintinstaller
Version: 0.15.2
Summary: UNKNOWN
Home-page: UNKNOWN
Author: Tarek Ziadé
Author-email: tarek@ziade.org
License: GPL
Platform: UNKNOWN
Classifier: Programming Language :: Python
Classifier: Topic :: Software Development :: Libraries :: Python Modules
